ipydatatable/__init__.py
ipydatatable/_frontend.py
ipydatatable/_table_trailet.py
ipydatatable/_version.py
ipydatatable/ipydatatable.py
ipydatatable/labextension/build_log.json
ipydatatable/labextension/package.json
ipydatatable/labextension/static/lib_index_js.316a90e0404f4eeeaeec.js
ipydatatable/labextension/static/lib_index_js.316a90e0404f4eeeaeec.js.map
ipydatatable/labextension/static/lib_plugin_js.23fd5c762b358e216fdf.js
ipydatatable/labextension/static/lib_plugin_js.23fd5c762b358e216fdf.js.map
ipydatatable/labextension/static/lib_widget_js.f3f34a18b72f45ab6122.js
ipydatatable/labextension/static/lib_widget_js.f3f34a18b72f45ab6122.js.map
ipydatatable/labextension/static/remoteEntry.f814c024b527832fa8b8.js
ipydatatable/labextension/static/remoteEntry.f814c024b527832fa8b8.js.map
ipydatatable/labextension/static/style.js
ipydatatable/labextension/static/vendors-node_modules_datatables_net-buttons_js_buttons_colVis_js-node_modules_datatables_net--d6e7f3.9afcf71db8c9b9999012.js
ipydatatable/labextension/static/vendors-node_modules_datatables_net-buttons_js_buttons_colVis_js-node_modules_datatables_net--d6e7f3.9afcf71db8c9b9999012.js.map
ipydatatable/nbextension/extension.js
ipydatatable/nbextension/index.js
ipydatatable/nbextension/index.js.LICENSE.txt
ipydatatable/nbextension/index.js.map
ipydatatable/tests/__init__.py
ipydatatable/tests/conftest.py
ipydatatable/tests/test_example.py
ipydatatable/tests/test_nbextension_path.py
ipydatatable-1.0.4.data/data/share/jupyter/labextensions/ipydatatable/build_log.json
ipydatatable-1.0.4.data/data/share/jupyter/labextensions/ipydatatable/package.json
ipydatatable-1.0.4.data/data/share/jupyter/labextensions/ipydatatable/static/lib_index_js.316a90e0404f4eeeaeec.js
ipydatatable-1.0.4.data/data/share/jupyter/labextensions/ipydatatable/static/lib_index_js.316a90e0404f4eeeaeec.js.map
ipydatatable-1.0.4.data/data/share/jupyter/labextensions/ipydatatable/static/lib_plugin_js.23fd5c762b358e216fdf.js
ipydatatable-1.0.4.dist-info/METADATA
ipydatatable-1.0.4.dist-info/WHEEL
ipydatatable-1.0.4.dist-info/licenses/LICENSE.txt
ipydatatable-1.0.4.dist-info/RECORD
